ovum/__init__.py
ovum/client.py
ovum/test.py
ovum/dto/ovum_dto.py
ovumpy-0.0.1.dist-info/LICENSE
ovumpy-0.0.1.dist-info/METADATA
ovumpy-0.0.1.dist-info/WHEEL
ovumpy-0.0.1.dist-info/top_level.txt
ovumpy-0.0.1.dist-info/RECORD
