Metadata-Version: 2.2
Name: ovumpy
Version: 0.0.1
Summary: A python package to interact with Ovum heatpumps.
Author-email: Florian Schlittenbauer <florian.schlittenbauer@gmail.com>
License: MIT License
Project-URL: Homepage, https://github.com/schliflo/ovumpy
Project-URL: Documentation, https://github.com/schliflo/ovumpy/wiki/
License-File: LICENSE
Requires-Dist: dataclasses_json>=0.6.7
Requires-Dist: httpx>=0.28.1
